setup.cfg
setup.py
hiplogging/__init__.py
hiplogging.egg-info/PKG-INFO
hiplogging.egg-info/SOURCES.txt
hiplogging.egg-info/dependency_links.txt
hiplogging.egg-info/requires.txt
hiplogging.egg-info/top_level.txt