Metadata-Version: 1.1
Name: hiplogging
Version: 2.0.0
Summary: HipChat support for the Python logging module
Home-page: https://github.com/invernizzi/hiplogging
Author: Luca Invernizzi
Author-email: invernizzi.l@gmail.com
License: MIT
Download-URL: https://github.com/invernizzi/hiplogging/tarball/2.0.0
Keywords: hipchat,log,logging
Platform: UNKNOWN
Classifier: Development Status :: 5 - Production/Stable
Classifier: Intended Audience :: Developers
Classifier: License :: OSI Approved :: MIT License
Classifier: Programming Language :: Python :: 2
Classifier: Programming Language :: Python :: 2.7
Classifier: Programming Language :: Python :: 3
